RNAseqt/__init__.py
RNAseqt/main.py
RNAseqt-1.1.0.dist-info/LICENSE
RNAseqt-1.1.0.dist-info/METADATA
RNAseqt-1.1.0.dist-info/WHEEL
RNAseqt-1.1.0.dist-info/entry_points.txt
RNAseqt-1.1.0.dist-info/top_level.txt
RNAseqt-1.1.0.dist-info/RECORD
