Metadata-Version: 2.1
Name: RNAseqt
Version: 1.1.0
Summary: A Python package to generate Snakemake workflow files
Home-page: https://github.com/qinti2023/RNAseqt
Author: qinti
Author-email: qinti@zju.edu.cn
Classifier: Programming Language :: Python :: 3
Classifier: License :: OSI Approved :: MIT License
Classifier: Operating System :: OS Independent
Requires-Python: >=3.6
License-File: LICENSE
